[
    {
        "id": "14527,14528",
        "owner": "0xfedd14d3a32faabfbd6e290faa73aec58e894650",
        "liquidity": 11273380948050225249259,
        "user": "DBRiMatt",
        "eth_in_lp": 0.07166629421662257,
        "donut_in_lp": 764219.9176432594,
        "percent_of_pool": 31.682540966835006
    },
    {
        "id": "11151,12344",
        "owner": "0x7f25555a0c85b53cb8934960d0e4ae2df65cecab",
        "liquidity": 7037018894282700541410,
        "user": "MemeyCurmudgeon",
        "eth_in_lp": 0.01856870054137836,
        "donut_in_lp": 630777.4816520443,
        "percent_of_pool": 19.7767325019797
    },
    {
        "id": "12389",
        "owner": "0x0e066ed845a6853557a0d580b3ba998b0283aca8",
        "liquidity": 3124555694263625859999,
        "user": "Eth_Man",
        "eth_in_lp": 0.9281917338159401,
        "donut_in_lp": 687529.6451506704,
        "percent_of_pool": 8.781204524432068
    },
    {
        "id": "10320",
        "owner": "0xdd4b43ffa5ceef9e5bf053ea9a74820b68e506d0",
        "liquidity": 2442176000488968169482,
        "user": null,
        "eth_in_lp": 0.0,
        "donut_in_lp": 710686.8895149705,
        "percent_of_pool": 6.863454853541093
    },
    {
        "id": "10151",
        "owner": "0x439cee4cc4ecbd75dc08d9a17e92bddcc11cdb8c",
        "liquidity": 2228164216679413715045,
        "user": "r/EthTrader Multi-Sig Wallet",
        "eth_in_lp": 3.324417780436422,
        "donut_in_lp": 1493409.1033043473,
        "percent_of_pool": 6.2619993417317135
    },
    {
        "id": "12430",
        "owner": "0x58edd08a8f51cea4c0faf176c71ab8c7c40ba1bc",
        "liquidity": 1337281836100304933934,
        "user": "Crypto_Gaming_",
        "eth_in_lp": 0.0821285533036155,
        "donut_in_lp": 422710.6533325292,
        "percent_of_pool": 3.7582768427407784
    },
    {
        "id": "12133",
        "owner": "0x4898c9503caedb585d4ffb41625a590baa348ee7",
        "liquidity": 1217001559690501812605,
        "user": null,
        "eth_in_lp": 0.0,
        "donut_in_lp": 91973.91805878791,
        "percent_of_pool": 3.420242955443205
    },
    {
        "id": "12521",
        "owner": "0x960a596e15913fda7040ea80fd43c2b8e8a1fe39",
        "liquidity": 1208348833941913341061,
        "user": "SuccessOtherwise2760",
        "eth_in_lp": 1.8028547081294795,
        "donut_in_lp": 809886.06453134,
        "percent_of_pool": 3.395925464597492
    },
    {
        "id": "12435,15863",
        "owner": "0x93d93069fbc8d0868b93c6be9383ed9f85392474",
        "liquidity": 891396749390956172687,
        "user": "Paper_cobbler",
        "eth_in_lp": 0.15048561435090746,
        "donut_in_lp": 140216.37040263403,
        "percent_of_pool": 2.5051680733956783
    },
    {
        "id": "15860",
        "owner": "0xe1e21819b7f2918980bb85f9f1892e835215a026",
        "liquidity": 869290775881109380806,
        "user": "Humble-Grape1012",
        "eth_in_lp": 0.0657604423615827,
        "donut_in_lp": 249141.11927495725,
        "percent_of_pool": 2.4430417765407295
    },
    {
        "id": "10922",
        "owner": "0x5f9d94cc0071acaf471ec711143085e0dcdf453a",
        "liquidity": 855853221911865214859,
        "user": "ALiteralHamSandwich",
        "eth_in_lp": 0.0,
        "donut_in_lp": 207208.21881087188,
        "percent_of_pool": 2.405277076129513
    },
    {
        "id": "12117",
        "owner": "0x0eafde159a21ca316e1fa7f64e7755e15b9c1349",
        "liquidity": 313157654672644511639,
        "user": "Yinyangkarma060910",
        "eth_in_lp": 0.0,
        "donut_in_lp": 47336.76567084633,
        "percent_of_pool": 0.88009358230372
    },
    {
        "id": "11043,17320",
        "owner": "0xeb9a6e724925b178d9627ce05208cfe6a5c11447",
        "liquidity": 290199853064243527036,
        "user": "Kappatalizable",
        "eth_in_lp": 0.04978443180379229,
        "donut_in_lp": 52534.73716004858,
        "percent_of_pool": 0.8155733205190391
    },
    {
        "id": "19264",
        "owner": "0xb89cb46a5cf811b99a3608c8b9e63ad0de990fe0",
        "liquidity": 264955142794422101193,
        "user": "Buzzalu",
        "eth_in_lp": 0.3953126888629949,
        "donut_in_lp": 177584.0484532044,
        "percent_of_pool": 0.7446259648849842
    },
    {
        "id": "12160",
        "owner": "0x35162a2ed27a8e2dc96471ab6fb63e0fd5058d46",
        "liquidity": 255600824181818749721,
        "user": "Soaring_Eagle590",
        "eth_in_lp": 0.0,
        "donut_in_lp": 45618.98710584587,
        "percent_of_pool": 0.718336727962507
    },
    {
        "id": "11843",
        "owner": "0x2a043f315f24762937cbcf0eb6cb313a43bde534",
        "liquidity": 232912851819685563042,
        "user": "raymv1987",
        "eth_in_lp": 0.03370743408929507,
        "donut_in_lp": 69394.15628861285,
        "percent_of_pool": 0.6545747902501097
    },
    {
        "id": "18694",
        "owner": "0xdb1032c4c3a3c81cd75a864dd85325cd85743218",
        "liquidity": 216106320874159086324,
        "user": null,
        "eth_in_lp": 0.03417207026024057,
        "donut_in_lp": 32932.64894393945,
        "percent_of_pool": 0.6073419674043496
    },
    {
        "id": "12124",
        "owner": "0x48afb64d55c79a2e711c14a2bf903a7c3842bacc",
        "liquidity": 186243770391645504024,
        "user": "Jake123194",
        "eth_in_lp": 0.03919044135177275,
        "donut_in_lp": 32163.403110053066,
        "percent_of_pool": 0.5234167028012715
    },
    {
        "id": "10319",
        "owner": "0xe86b79c26338fc514013eecb042a9f42ff9d12af",
        "liquidity": 184332395022271176408,
        "user": null,
        "eth_in_lp": 0.0,
        "donut_in_lp": 53108.04113277824,
        "percent_of_pool": 0.5180450020912307
    },
    {
        "id": "12157",
        "owner": "0xb127e23bf80e0d8688d994c1a093e3657856a040",
        "liquidity": 177455463780934649998,
        "user": "fairysquirt",
        "eth_in_lp": 0.0,
        "donut_in_lp": 53213.14207305203,
        "percent_of_pool": 0.49871817753134257
    },
    {
        "id": "10775",
        "owner": "0x9af25ff741763b43f67be449329a3a607799bff1",
        "liquidity": 134649276529132478151,
        "user": "Budget_Muffin7766",
        "eth_in_lp": 0.002403352948270381,
        "donut_in_lp": 44431.89851696501,
        "percent_of_pool": 0.37841631001804843
    },
    {
        "id": "11281",
        "owner": "0xe120ffc02ff9e6685ad3d65f998d8e40b4578a17",
        "liquidity": 113006991333331770994,
        "user": "Sharkytrs",
        "eth_in_lp": 0.005315584152848779,
        "donut_in_lp": 36513.587511659156,
        "percent_of_pool": 0.31759315585590026
    },
    {
        "id": "11090",
        "owner": "0x12985951fa7051f0b1ae2c0749c8285bd742a82b",
        "liquidity": 108692040369037891095,
        "user": "Haruhi4",
        "eth_in_lp": 0.02833321613171858,
        "donut_in_lp": 72849.85532240683,
        "percent_of_pool": 0.30546648229398454
    },
    {
        "id": "12264",
        "owner": "0xeca23ebdfdf663d499891a833d22956a6f65dfa2",
        "liquidity": 78823009636659006949,
        "user": "Kindly-Wolf6919",
        "eth_in_lp": 0.048520572222234014,
        "donut_in_lp": 52830.4080833414,
        "percent_of_pool": 0.2215230056937444
    },
    {
        "id": "11832",
        "owner": "0x7b34db486502f78afb65769f7b53f57337b87084",
        "liquidity": 78588437751231643566,
        "user": "vanboiDallas",
        "eth_in_lp": 0.01137341527092331,
        "donut_in_lp": 23414.673295954035,
        "percent_of_pool": 0.2208637683802918
    },
    {
        "id": "12986",
        "owner": "0xf3a6ab4ab31ab110b272b238a5e29160c9804c05",
        "liquidity": 72130053692756336819,
        "user": "Pibo1987",
        "eth_in_lp": 0.00021886279603791875,
        "donut_in_lp": 8283.737601279645,
        "percent_of_pool": 0.2027132225542335
    },
    {
        "id": "10499",
        "owner": "0x1fec4923925f96f02634281260f4555cc802ec6a",
        "liquidity": 70159062604761204836,
        "user": null,
        "eth_in_lp": 0.10467721967531189,
        "donut_in_lp": 47023.54610532061,
        "percent_of_pool": 0.19717397872148845
    },
    {
        "id": "10350",
        "owner": "0x349cb3d3db85a1bff571ecaaaff4cff48503cd54",
        "liquidity": 70078717533468007684,
        "user": "likelysomeone3",
        "eth_in_lp": 0.10455734494544318,
        "donut_in_lp": 46969.69546900901,
        "percent_of_pool": 0.19694817813651222
    },
    {
        "id": "11918",
        "owner": "0x8d23dbae8e5c52d9ac2bb5f393c4ff2e228abae6",
        "liquidity": 37673432651864763160,
        "user": "BuddhaIvan",
        "eth_in_lp": 0.056208706889916374,
        "donut_in_lp": 25250.314520742064,
        "percent_of_pool": 0.10587685086260133
    },
    {
        "id": "11303",
        "owner": "0x7ea45e32a4f75f79615e1c77fa017f2ac4fe66ab",
        "liquidity": 34725575817112479836,
        "user": "Savi321",
        "eth_in_lp": 0.0026269336916400375,
        "donut_in_lp": 11692.785762717225,
        "percent_of_pool": 0.09759223816639355
    },
    {
        "id": "10408",
        "owner": "0x57855ca297ecb91ef1be3ce1e74b9492cf50c69c",
        "liquidity": 31368080584687035142,
        "user": "nobelcause",
        "eth_in_lp": 0.0014754810308100423,
        "donut_in_lp": 12628.197490465536,
        "percent_of_pool": 0.08815638385281514
    },
    {
        "id": "11084",
        "owner": "0xdf2ffb4a4c766a322f1fbe6a6e344ca018bdec9e",
        "liquidity": 22040020818175638771,
        "user": "Huelino",
        "eth_in_lp": 0.0010367109504223761,
        "donut_in_lp": 7121.331338956543,
        "percent_of_pool": 0.061940944398097095
    },
    {
        "id": "12368",
        "owner": "0x1b036f17f5dcb000005e14773f8636b4dde76e39",
        "liquidity": 19420562577934090692,
        "user": null,
        "eth_in_lp": 0.0006314846212036445,
        "donut_in_lp": 1901.8742340006386,
        "percent_of_pool": 0.054579258193239444
    },
    {
        "id": "10342",
        "owner": "0xcbedbe4f7b04def3b4ddb581c266a0c45023d99f",
        "liquidity": 18062036536701212097,
        "user": "InsaneMcFries",
        "eth_in_lp": 0.026948532322714852,
        "donut_in_lp": 12105.934376921336,
        "percent_of_pool": 0.05076127695458388
    },
    {
        "id": "10485",
        "owner": "0xdb721582dc092c59692221d89103061c8b955d7c",
        "liquidity": 17531494615859564964,
        "user": "whaterloowhorks",
        "eth_in_lp": 0.026156964546107556,
        "donut_in_lp": 11750.342931578827,
        "percent_of_pool": 0.04927024988655988
    },
    {
        "id": "13743",
        "owner": "0x10006c92af4c697db4d168cb4e2c56009450a493",
        "liquidity": 15498397994276458898,
        "user": "ellileon",
        "eth_in_lp": 0.00870034553840626,
        "donut_in_lp": 10387.660842308967,
        "percent_of_pool": 0.04355646559241863
    },
    {
        "id": "10500",
        "owner": "0x99a70e53a43775c8af35884e2b74414ef09ca7f3",
        "liquidity": 15169566371622676832,
        "user": "EvolvedLurker",
        "eth_in_lp": 0.0009316319916358296,
        "donut_in_lp": 10167.264426394557,
        "percent_of_pool": 0.04263232212526106
    },
    {
        "id": "12058",
        "owner": "0x53577b2a5c8db082524caf0a980eec182fe17341",
        "liquidity": 9550009794175007171,
        "user": null,
        "eth_in_lp": 0.00392286975599546,
        "donut_in_lp": 6400.807542770171,
        "percent_of_pool": 0.02683920448815806
    },
    {
        "id": "11096",
        "owner": "0x1a86440fd49a1e85c46c66ba64c46b98b0e3b6ab",
        "liquidity": 8779210294839764061,
        "user": "evil_betty_",
        "eth_in_lp": 0.0,
        "donut_in_lp": 5177.438882606534,
        "percent_of_pool": 0.024672961120046882
    },
    {
        "id": "16655",
        "owner": "0x527a12dbc1fe652568457d64826541f25241d5a8",
        "liquidity": 7595209121609858683,
        "user": null,
        "eth_in_lp": 0.0,
        "donut_in_lp": 4999.9999999964275,
        "percent_of_pool": 0.021345461956441925
    },
    {
        "id": "11875",
        "owner": "0xff98aa744a746933f366ca2cf0eb1338f9e5eb36",
        "liquidity": 4827465707478737818,
        "user": "PineapplePie135",
        "eth_in_lp": 0.007202571835708846,
        "donut_in_lp": 3235.569972567954,
        "percent_of_pool": 0.013567037319859122
    },
    {
        "id": "10302,12674",
        "owner": "0x6b82a00010676e509e520ff4594eeb2005de93de",
        "liquidity": 4439414593844977513,
        "user": "CapnPratt",
        "eth_in_lp": 6.341194458828822e-05,
        "donut_in_lp": 1311.5398229868506,
        "percent_of_pool": 0.01247646428222449
    },
    {
        "id": "10298",
        "owner": "0x5ed61dee19b3355cf125a5cb95bec8f344523628",
        "liquidity": 1555692245851803899,
        "user": "DrRobbe",
        "eth_in_lp": 0.002321090575049351,
        "donut_in_lp": 1042.6901861647393,
        "percent_of_pool": 0.004372094187016002
    },
    {
        "id": "10344",
        "owner": "0x0b3ab5a8d926d07275291c074225f258d00b4f08",
        "liquidity": 1286606737294797967,
        "user": "The_Nutcrack",
        "eth_in_lp": 0.00015118374854413447,
        "donut_in_lp": 862.3365091917044,
        "percent_of_pool": 0.003615860304055322
    },
    {
        "id": "10250",
        "owner": "0x8dfdd8e1f2ea3f70c7a5f0a42903a8239a83d313",
        "liquidity": 1164637462377409575,
        "user": "Ok_Election7896",
        "eth_in_lp": 0.0017376374051369472,
        "donut_in_lp": 780.5888701308157,
        "percent_of_pool": 0.0032730796806493805
    },
    {
        "id": "12420",
        "owner": "0x3808699baf43ba988d1e9acd64237dea36c61593",
        "liquidity": 65162551889730903,
        "user": null,
        "eth_in_lp": 9.722243293345222e-05,
        "donut_in_lp": 43.67467507924149,
        "percent_of_pool": 0.00018313185984431557
    }
]